azure/mgmt/confidentialledger/__init__.py
azure/mgmt/confidentialledger/_confidential_ledger.py
azure/mgmt/confidentialledger/_configuration.py
azure/mgmt/confidentialledger/_patch.py
azure/mgmt/confidentialledger/_vendor.py
azure/mgmt/confidentialledger/_version.py
azure/mgmt/confidentialledger/py.typed
azure/mgmt/confidentialledger/aio/__init__.py
azure/mgmt/confidentialledger/aio/_confidential_ledger.py
azure/mgmt/confidentialledger/aio/_configuration.py
azure/mgmt/confidentialledger/aio/_patch.py
azure/mgmt/confidentialledger/aio/operations/__init__.py
azure/mgmt/confidentialledger/aio/operations/_confidential_ledger_operations.py
azure/mgmt/confidentialledger/aio/operations/_ledger_operations.py
azure/mgmt/confidentialledger/aio/operations/_operations.py
azure/mgmt/confidentialledger/models/__init__.py
azure/mgmt/confidentialledger/models/_confidential_ledger_enums.py
azure/mgmt/confidentialledger/models/_models_py3.py
azure/mgmt/confidentialledger/operations/__init__.py
azure/mgmt/confidentialledger/operations/_confidential_ledger_operations.py
azure/mgmt/confidentialledger/operations/_ledger_operations.py
azure/mgmt/confidentialledger/operations/_operations.py
azure_mgmt_confidentialledger-1.0.0.dist-info/LICENSE
azure_mgmt_confidentialledger-1.0.0.dist-info/METADATA
azure_mgmt_confidentialledger-1.0.0.dist-info/WHEEL
azure_mgmt_confidentialledger-1.0.0.dist-info/top_level.txt
azure_mgmt_confidentialledger-1.0.0.dist-info/RECORD
